{"fmnztKsvOTf5oTKXH4vArQ==":"logo.jpg","zhoOacY2AmLYDZ2AJUs66g==":"carusel3.jpeg","MjYyDcgtYACmMh5DyfU4SA==":"carusel2.jpg","a5FSGSxCRNMzb+GdZVwF2g==":"carusel1.jpg","u7IpDFY/pHHPJzT88RS8EA==":"carusel1-1.jpg","4HX7KsWK7Yakaa3C7BPN/A==":"carusel1-1.jpeg","MZ95B0KdnMvlTsUpFKXv3w==":"header-1890x1260.jpg","kk3UFfif7O7lFRk9667uIg==":"opem-769x513.jpg","hQWHbgA757ZvoN83Zha34g==":"photo-1513618364580-fe1596762e8e-769x1154.jpg","RwPWSZy/AhKVM/EVs20rTQ==":"kitchen-769x962.jpg","/L/nVED/FVxhsCR+J9/l/A==":"carusel2-1511x756.jpg","PP1DinW26kggBnc5Ya0ypA==":"carusel4-1189x594.jpg","7cvPQF4oyvczzLkNyGzZiA==":"carusel3-1512x756.jpg","4pafa8y42QfT8v4W+oqtUQ==":"alexandra-namila-160x160.jpg","Dpd5R81tx5qJP7RbyMyrzQ==":"filip-bianco-160x160.jpg","+7zQCP4Gde0NPb3uDG1JTA==":"mircea-sipic-160x160.jpg","DjsGupJm/yTMoXOlqiRBZw==":"tudor-pilipic-160x160.jpg","X9TKJbXV6RsngaMZrCmRYg==":"mircea-saliman-1050x1050.jpg","/AkqRS3xwTHxWQU/o++r6g==":"monika-calbina-1050x1050.jpg","fRymbTo7J4W/5NdNWW3Ctg==":"alexandra-namila-1050x1050.jpg","ZTTpqXCAPtquwsGxTN+2YQ==":"anne-felci-160x160.jpg","ujEj+hyDmYs6K4zuttxTWA==":"emil-stoianca(21)-160x160.jpg","T7JlOT8uz++hgbmMVvgzgQ==":"asis-peliman-160x160.jpg","XqStexa3ucYeWEdbgE9USg==":"background1.jpg","fiVBQ6pj9eVKER0jbRA+pw==":"guacamole-393x262.jpg","Xg7KQ/1Z9FD6LAeUGbr0dg==":"nachos-393x326.jpg","O/wNfUpcK0RMKaOhQ/IPfg==":"guacamole-393x262.jpeg","9PxVEGO1S5Bz/He13jp1iA==":"guacamole-1-393x262.jpeg","tCrDq2yO2gOeKPJGltB8+g==":"taco-393x475.jpg","SpsDtoDZIkgmzZIPfpZ/GA==":"guacamole-578x385.jpg","KRPY1gsn1SGda420MJMr/Q==":"guacamole-448x448.jpg","bgVoK61h/sZhra5nvNGO9Q==":"nachos-448x448.jpg","CEGi4EniGyy9M3Gj0DW4XQ==":"taco-448x448.jpg","UQ7YQpEkaFy7YBuA+ZOY0g==":"burrito-540x540.jpg","hkZcIxtb/Y94wooYs4W+rQ==":"header-1-1890x1260.jpg","eZDQnEPWkDil2CZv2EB54Q==":"salata-448x359.jpg","a54MrF9oBE+hzRCI9wjuIQ==":"pastaaaa-448x358.jpg","BKaFs16m7daX95HkVpmjAQ==":"pasta-448x359.jpg","Pb8FgIjb7PnZw3K1oZd8sQ==":"pizza-1170x936.jpg","lgxDQWQXjc6/ZIYmS6esJQ==":"bbq-cichin-448x448.jpg","DQFCcKaoZjn6rEiLgJ+WCA==":"burger-448x448.jpg","BNz2V7qO6ox2QWN2bOCcjg==":"clatite-448x448.jpg","ClhtTJHKywVbcMNe2sEXcw==":"gogosi-960x960.jpg","nmnxzJdOpaYWchjbFxTAQg==":"eat-1114x743.jpg","3QWV1ZMVP8ZUVfNfMdIL5Q==":"even7-1152x1152.jpg","2/Iz+I0drNqe2GEU7ytGYg==":"even8-1152x1152.jpg","VT2wcEmybRYY/DV+VlMLhA==":"even1-427x427.jpg","Potk7LZoedm4gX5am1/nPw==":"even3-448x448.jpg","qHv9wjJQBwUeh9zwxVr40A==":"carusel1-1500x750.jpeg","+QAJWBsSWXSnlHFM6Kf1bA==":"dinner-1114x668.jpg","cdK2JpjsQe5QeB51xJmlhQ==":"header-1-1890x1260.jpeg","FFfYaPGTd03IhpnhhllWaA==":"tigai-1114x743.jpeg","Eq/VnxiDnmF2VRyn3pgxjQ==":"eat-1114x743.jpeg","73HjcmgtddUmEdnQ/I76Xg==":"dinner-1114x668.jpeg","CbZmcuW9RyvoU0EB3I2deg==":"eat-1-1114x743.jpeg","RpAhQINREX7xb4FUkzixKA==":"eat-1604x902.jpg"}